githubstar/__init__.py
githubstar/fileexporter.py
githubstar/githubstar.py
githubstar/starredfetcher.py
githubstar/topicsinfo.py
githubstar/utils.py
githubstar/version.py
githubstar-1.1.0.dist-info/licenses/LICENSE
githubstar-1.1.0.dist-info/METADATA
githubstar-1.1.0.dist-info/WHEEL
githubstar-1.1.0.dist-info/entry_points.txt
githubstar-1.1.0.dist-info/top_level.txt
githubstar-1.1.0.dist-info/RECORD
