Metadata-Version: 2.4
Name: githubstar
Version: 1.1.0
Summary: Export Github starred repos list to file
Author: avalogic@github
License: MIT License
Project-URL: Homepage, https://github.com/avalogic/githubstar
Keywords: github,star,stars,starred,export
Classifier: Intended Audience :: Developers
Classifier: Programming Language :: Python
Classifier: Programming Language :: Python :: 3.13
Classifier: License :: OSI Approved :: MIT License
Classifier: Operating System :: OS Independent
Requires-Python: >=3.13
License-File: LICENSE
Requires-Dist: PyGithub<2.0.0,>=1.59.1
Dynamic: license-file
